AUTHORS
CHANGES
LICENSE
MANIFEST.in
Makefile
setup.cfg
setup.py
artwork/LICENSE
artwork/logo-full.svg
artwork/logo-lineart.svg
docs/.gitignore
docs/Makefile
docs/advanced_foreword.rst
docs/api.rst
docs/appcontext.rst
docs/becomingbig.rst
docs/blueprints.rst
docs/changelog.rst
docs/cli.rst
docs/conf.py
docs/config.rst
docs/contents.rst.inc
docs/design.rst
docs/errorhandling.rst
docs/extensiondev.rst
docs/extensions.rst
docs/flaskdocext.py
docs/flaskext.py
docs/flaskstyle.sty
docs/foreword.rst
docs/htmlfaq.rst
docs/index.rst
docs/installation.rst
docs/latexindex.rst
docs/license.rst
docs/logo.pdf
docs/make.bat
docs/python3.rst
docs/quickstart.rst
docs/reqcontext.rst
docs/security.rst
docs/server.rst
docs/shell.rst
docs/signals.rst
docs/styleguide.rst
docs/templating.rst
docs/testing.rst
docs/unicode.rst
docs/upgrading.rst
docs/views.rst
docs/_static/debugger.png
docs/_static/flask-favicon.ico
docs/_static/flask.png
docs/_static/flaskr.png
docs/_static/logo-full.png
docs/_static/no.png
docs/_static/touch-icon.png
docs/_static/yes.png
docs/_templates/sidebarintro.html
docs/_templates/sidebarlogo.html
docs/deploying/cgi.rst
docs/deploying/fastcgi.rst
docs/deploying/index.rst
docs/deploying/mod_wsgi.rst
docs/deploying/uwsgi.rst
docs/deploying/wsgi-standalone.rst
docs/patterns/apierrors.rst
docs/patterns/appdispatch.rst
docs/patterns/appfactories.rst
docs/patterns/caching.rst
docs/patterns/celery.rst
docs/patterns/deferredcallbacks.rst
docs/patterns/distribute.rst
docs/patterns/errorpages.rst
docs/patterns/fabric.rst
docs/patterns/favicon.rst
docs/patterns/fileuploads.rst
docs/patterns/flashing.rst
docs/patterns/index.rst
docs/patterns/jquery.rst
docs/patterns/lazyloading.rst
docs/patterns/methodoverrides.rst
docs/patterns/mongokit.rst
docs/patterns/packages.rst
docs/patterns/requestchecksum.rst
docs/patterns/sqlalchemy.rst
docs/patterns/sqlite3.rst
docs/patterns/streaming.rst
docs/patterns/subclassing.rst
docs/patterns/templateinheritance.rst
examples/flaskr/flaskr.egg-info/PKG-INFO
examples/flaskr/flaskr.egg-info/SOURCES.txt
examples/flaskr/flaskr.egg-info/dependency_links.txt
examples/flaskr/flaskr.egg-info/requires.txt
examples/flaskr/flaskr.egg-info/top_level.txt
examples/minitwit/minitwit.egg-info/PKG-INFO
examples/minitwit/minitwit.egg-info/SOURCES.txt
examples/minitwit/minitwit.egg-info/dependency_links.txt
examples/minitwit/minitwit.egg-info/requires.txt
examples/minitwit/minitwit.egg-info/top_level.txt
flaskmodificado.egg-info/PKG-INFO
flaskmodificado.egg-info/SOURCES.txt
flaskmodificado.egg-info/dependency_links.txt
flaskmodificado.egg-info/entry_points.txt
flaskmodificado.egg-info/not-zip-safe
flaskmodificado.egg-info/requires.txt
flaskmodificado.egg-info/top_level.txt
