Metadata-Version: 1.1
Name: flaskmodificado
Version: 0.1
Summary: Flask modificadoand good intentions
Home-page: https://gitlab.com/israelblender/flask_modificado
Author: Israel Blender
Author-email: israelgomes.prog@gmail.com
License: MIT
Download-URL: https://gitlab.com/israelblender/flask_modificado/repository/archive.tar.gz?ref=0.1
Platform: any
Classifier: Development Status :: 4 - Beta
Classifier: Environment :: Web Environment
Classifier: Intended Audience :: Developers
Classifier: License :: OSI Approved :: BSD License
Classifier: Operating System :: OS Independent
Classifier: Programming Language :: Python
Classifier: Programming Language :: Python :: 2
Classifier: Programming Language :: Python :: 2.6
Classifier: Programming Language :: Python :: 2.7
Classifier: Programming Language :: Python :: 3
Classifier: Programming Language :: Python :: 3.3
Classifier: Programming Language :: Python :: 3.4
Classifier: Programming Language :: Python :: 3.5
Classifier: Topic :: Internet :: WWW/HTTP :: Dynamic Content
Classifier: Topic :: Software Development :: Libraries :: Python Modules
